Workbook

Sheet Content Inventory
A1: Day | B1: Module # | C1: Session or Module Name | D1: Estimated Minutes | E1: Content Type | F1: Artifact Type 1 | G1: Artifact Type 2 | H1: Artifact Type 3 | I1: Learner Outcome in Plain Language | J1: Decisions the Learner Must Make | K1: Systems or Tools Touched | L1: Notes | M1: Status
A2: 3 | B2: D3.01 | C2: Welcome & Billing Overview | D2: 15 | E2: ILT | F2: Facilitator Guide | G2: Slide Deck | I2: I understand what Conservice does, what the billing role expects of me, how I'm supposed to behave during training, and how to ask good questions when I'm stuck. | J2: Which of the BOB tenets will be hardest for me to live out and why? When do I try to solve a problem on my own versus asking for help? What does 'owning the experience' look like for me personally? | K2: Zoom | M2: Built
A3: 3 | B3: D3.02 | C3: The Big Picture: 6-Step Billing Lifecycle | D3: 90 | E3: ILT | F3: Facilitator Guide | G3: Slide Deck | I3: I understand the 6-step billing lifecycle, how my daily work connects to client outcomes, what my performance will be measured by, and why every step depends on the one before it. | J3: Which BOB tenet will stretch me most and why? Who ultimately pays for our services — the resident or the property manager? Why is chat responsiveness tied to client outcomes, not just professionalism? What is missing from this question before I ask it? Which of the five core skills am I strongest in, and which do I need to work on? | K3: Zoom, HRX | M3: Built
A4: 3 | B4: D3.03 | C4: Tool Navigation | D4: 45 | E4: Blended | F4: Facilitator Guide | G4: eLearning Module | H4: Knowledge Base Article | I4: I know where each system lives in the billing workflow, how to open and navigate a task in Skywalker, how to pull up a bill in Foxit, and where provider data gets entered in Fusion — so I don't get lost on my first real task. | J4: Which system do I open first for this task? Am I in the right tab in Skywalker before I start entering data? Does this bill in Foxit match the account and cycle I'm working on? Is there a CSR Alert I need to read before I can move forward? | K4: Skywalker, Foxit, Fusion 2.0, Email/Inbox, Knowledge Base | M4: Built
A5: 3 | B5: D3.04 | C5: Inbox & Macro Setup | D5: 30 | E5: ILT | F5: Job Aid | G5: Facilitator Guide | I5: ⚠️ DRAFT — I can configure my Outlook/Gmail inbox with the folders, filters, and macros I'll use every day so my email doesn't become a bottleneck. | J5: ⚠️ DRAFT — Which emails get filtered automatically vs. need my attention? Which macros do I set up first? | K5: Email/Inbox, Outlook or Gmail | L5: Setup task — pair with IT/onboarding checklist | M5: Draft
A6: 3 | B6: D3.05 | C6: Intro to Provider Bills: Reading Key Bill Elements | D6: 40 | E6: ILT | F6: Facilitator Guide | G6: Slide Deck | H6: Sample Bills | I6: ⚠️ DRAFT — I can identify the key elements on a provider bill (account number, service period, charges, usage) and know which fields matter for prep work. | J6: ⚠️ DRAFT — Is this the right bill for the right cycle? Which charges are billable to residents vs. property? | K6: Foxit, Provider portals | L6: Pair with sample bills from real providers | M6: Draft
A7: 3 | B7: D3.06 | C7: Distinguishing Similar-Looking Values on a Bill | D7: 30 | E7: ILT | F7: Activity | G7: Sample Bills | I7: ⚠️ DRAFT — I can tell the difference between values that look similar on a provider bill (current charges vs. previous balance, total due vs. amount billed) so I enter the right number. | J7: ⚠️ DRAFT — Which value am I supposed to enter into Fusion? Does the number on the bill match what I'm about to type? | K7: Foxit, Fusion 2.0 | L7: High-repetition activity recommended | M7: Draft
A8: 3 | B8: D3.07 | C8: Prep — Fusion 2.0 & Spreadsheet Simulations | D8: 60 | E8: Simulation | F8: Facilitator Guide | G8: Job Aid | I8: ⚠️ DRAFT — I can complete a prep task in Fusion 2.0 and on a holding spreadsheet, knowing when to use which and how the two connect. | J8: ⚠️ DRAFT — Fusion or spreadsheet for this prop? Did I check the Fusion notes before entering data? | K8: Fusion 2.0, Spreadsheets, YODA | M8: Draft
A9: 3 | B9: D3.08 | C9: Data Entry Accuracy: Common Failure Points & QC Habits | D9: 30 | E9: ILT | F9: Job Aid | G9: Facilitator Guide | I9: ⚠️ DRAFT — I know the top sources of data entry errors in Fusion 2.0 and the habits that catch them before they leave my desk. | J9: ⚠️ DRAFT — Did I double-check this entry? What's my self-QC habit for each field? | K9: Fusion 2.0 | L9: Ties to AQC 80% target | M9: Draft
A10: 3 | B10: D3.09 | C10: NB / NUFB / State Regulations | D10: 15 | E10: ILT | F10: Facilitator Guide | G10: Reference Doc | I10: ⚠️ DRAFT — I know what NB and NUFB mean and where state regulations affect what we can and can't bill. | J10: ⚠️ DRAFT — Is this property in a regulated state? Does this charge comply? | K10: Knowledge Base, YODA | L10: Awareness-level only on Day 3 | M10: Draft
A11: 3 | B11: D3.10 | C11: Client Communication — Introduction to Professional Email & Why It Matters | D11: 30 | E11: ILT | F11: Facilitator Guide | G11: Slide Deck | H11: Mock Email Template | I11: ⚠️ DRAFT — I understand why client communication matters at Conservice, the elements of a professional email, and when to ask for help instead of guessing. | J11: ⚠️ DRAFT — Is this email professional enough to send? Do I need to loop in my lead? | K11: Email, Knowledge Base | L11: Foundation for Day 4+ mock email practice | M11: Draft
A12: 3 | B12: D3.11 | C12: EOD 3 Review | D12: 15 | E12: ILT | F12: Facilitator Guide | I12: ⚠️ DRAFT — I can name the 6 lifecycle steps, the 6 core systems, and the BOB tenets without prompting. | J12: ⚠️ DRAFT — What did I learn today that I need to revisit tonight? | K12: Zoom | L12: Daily close-out | M12: Draft
A13: 4 | B13: D4.01 | C13: Day 4 Morning Review | D13: 15 | E13: ILT | F13: Facilitator Guide | I13: ⚠️ DRAFT — I can recall the key Day 3 concepts and ask questions on anything that didn't stick. | J13: ⚠️ DRAFT — What from yesterday do I need clarification on? | K13: Zoom | L13: Daily warm-up | M13: Draft
A14: 4 | B14: D4.02 | C14: Intro to Skywalker | D14: 45 | E14: ILT | F14: Facilitator Guide | G14: Slide Deck | H14: Job Aid | I14: ⚠️ DRAFT — I can log into Skywalker, navigate the main views, and understand how it differs from YODA. | J14: ⚠️ DRAFT — Skywalker or YODA for this task? | K14: Skywalker | M14: Draft
A15: 4 | B15: D4.03 | C15: Bill Methods & Bill Setup — High-Level Introduction | D15: 45 | E15: ILT | F15: Facilitator Guide | G15: Slide Deck | I15: ⚠️ DRAFT — I understand the major bill methods at a high level and know where bill setup lives in the system. | J15: ⚠️ DRAFT — Which method applies to this property? | K15: YODA, Skywalker | L15: Depth comes Day 6-7 | M15: Draft
A16: 4 | B16: D4.04 | C16: Regulations | D16: 20 | E16: ILT | F16: Facilitator Guide | G16: Reference Doc | I16: ⚠️ DRAFT — I know the categories of state regulations that affect billing and where to look them up. | J16: ⚠️ DRAFT — Is this state regulated? Where do I check? | K16: Knowledge Base | M16: Draft
A17: 4 | B17: D4.05 | C17: Bill Dates Tab (2 Part) | D17: 60 | E17: ILT | F17: Facilitator Guide | G17: Slide Deck | H17: Dev YODA Practice | I17: I can correctly set bill dates in YODA — rent dates, Conservice utility dates, post month, and total date range — and I know when to flag a date that doesn't look right. | J17: Does the post month match the cycle? Are rent and Conservice dates aligned? Do I need to escalate this date setup? | K17: YODA, Dev YODA | L17: Krista pending on Dev YODA property access | M17: Built
A18: 4 | B18: D4.06 | C18: Future Cycle Calculator (FCC) | D18: 30 | E18: ILT | F18: Facilitator Guide | G18: Job Aid | I18: ⚠️ DRAFT — I know what FCC is, what it does, and that I'll learn the mechanics in Day 8 Exceptions. | J18: ⚠️ DRAFT — Awareness only — when would I use FCC? | K18: YODA | L18: Mechanics deferred to Day 8 | M18: Draft
A19: 4 | B19: D4.07 | C19: MIMO: What It Is and Where It Falls in the Workflow | D19: 30 | E19: ILT | F19: Facilitator Guide | G19: Slide Deck | I19: ⚠️ DRAFT — I understand what MIMO (Move-In/Move-Out) is and where it fits in the billing workflow. | J19: ⚠️ DRAFT — Is this a MIMO scenario? What does the cycle look like? | K19: YODA, Skywalker | L19: Deeper dive Day 5/7 | M19: Draft
A20: 4 | B20: D4.08 | C20: Scenario — Troubleshoot a Bill Dates Task | D20: 30 | E20: Scenario | F20: Facilitator Guide | G20: Scenario Card | I20: ⚠️ DRAFT — I can work through a bill dates scenario and identify what's wrong before fixing it. | J20: ⚠️ DRAFT — What's wrong here? What's my next move? | K20: YODA, Skywalker | M20: Draft
A21: 4 | B21: D4.09 | C21: Simulation — SW Bill Dates Task Error / Manual Bill Dates Exception | D21: 45 | E21: Simulation | F21: Facilitator Guide | G21: Job Aid | I21: ⚠️ DRAFT — I can resolve a Skywalker bill dates task error and a manual bill dates exception in YODA. | J21: ⚠️ DRAFT — What's the exception telling me? What's the fix? | K21: Skywalker, YODA | M21: Draft
A22: 4 | B22: D4.10 | C22: Client Communication — Grading Rubric, BOB Tenets, Mock Emails | D22: 30 | E22: Activity | F22: Facilitator Guide | G22: Rubric | H22: Mock Email Set | I22: ⚠️ DRAFT — I can write a professional client email and self-assess it against the grading rubric tied to BOB tenets. | J22: ⚠️ DRAFT — Does my email meet the rubric? Which tenet does it reflect? | K22: Email | L22: Rubric introduced here, used Day 5-10 | M22: Draft
A23: 4 | B23: D4.11 | C23: EOD 4 Review | D23: 15 | E23: ILT | F23: Facilitator Guide | I23: ⚠️ DRAFT — I can summarize bill dates, FCC awareness, and Skywalker basics from today. | J23: ⚠️ DRAFT — What do I revisit tonight? | K23: Zoom | L23: 1.5 practice / 1 hr admin time in afternoon | M23: Draft
A24: 5 | B24: D5.01 | C24: Day 5 Morning Review | D24: 15 | E24: ILT | F24: Facilitator Guide | I24: ⚠️ DRAFT — I can recall Day 4 concepts and ask follow-up questions. | J24: ⚠️ DRAFT — What needs clarification? | K24: Zoom | M24: Draft
A25: 5 | B25: D5.02 | C25: Billing Process Overview | D25: 45 | E25: ILT | F25: Facilitator Guide | G25: Slide Deck | I25: ⚠️ DRAFT — I can walk through the end-to-end billing process and place each Day 5 topic within it. | J25: ⚠️ DRAFT — Where in the process am I right now? | K25: YODA, Skywalker | L25: Anchors UA and Stats discussions | M25: Draft
A26: 5 | B26: D5.03 | C26: MIMO & Stats Tabs — Introduction | D26: 45 | E26: ILT | F26: Facilitator Guide | G26: Job Aid | I26: ⚠️ DRAFT — I can navigate the MIMO and Stats tabs in YODA and explain what each one drives. | J26: ⚠️ DRAFT — Are the stats correct? Did MIMO process cleanly? | K26: YODA | M26: Draft
A27: 5 | B27: D5.04 | C27: Utility Amounts Tab | D27: 60 | E27: ILT | F27: Facilitator Guide | G27: Job Aid | H27: Simulation | I27: ⚠️ DRAFT — I can verify and enter admin/flat amounts, RUBS provider amounts, and check frequency in the UA tab. | J27: ⚠️ DRAFT — Does this UA entry match the bill? Is the frequency right? | K27: YODA, Fusion 2.0 | M27: Draft
A28: 5 | B28: D5.05 | C28: Inputting Provider Amounts | D28: 45 | E28: Simulation | F28: Facilitator Guide | G28: Job Aid | I28: ⚠️ DRAFT — I can input provider amounts from a bill into UA correctly the first time. | J28: ⚠️ DRAFT — Right amount? Right line? Right frequency? | K28: YODA, Fusion 2.0, Foxit | M28: Draft
A29: 5 | B29: D5.06 | C29: Comparing UA Admin Amounts to Bill Setup / Fee Screen | D29: 30 | E29: ILT | F29: Facilitator Guide | G29: Job Aid | I29: ⚠️ DRAFT — I can compare UA admin amounts to Bill Setup and the Fee Screen and spot mismatches. | J29: ⚠️ DRAFT — Do these three agree? If not, which is right? | K29: YODA | M29: Draft
A30: 5 | B30: D5.07 | C30: What Good Documentation Looks Like | D30: 20 | E30: ILT | F30: Facilitator Guide | G30: Example Notes | I30: ⚠️ DRAFT — I know what a good Fusion/YODA note looks like, why it matters downstream, and the standards I'm expected to meet. | J30: ⚠️ DRAFT — Will the next person reading this note know what I did and why? | K30: YODA, Fusion 2.0 | L30: Sets foundation for exception notes Day 8 | M30: Draft
A31: 5 | B31: D5.08 | C31: Scenario — Base Fee / Service Fee Change or Unusual Cycle Length | D31: 30 | E31: Scenario | F31: Facilitator Guide | G31: Scenario Card | I31: ⚠️ DRAFT — I can work through a scenario involving a fee change or odd cycle and identify what to flag. | J31: ⚠️ DRAFT — What changed? Why? Who needs to know? | K31: YODA, Skywalker | M31: Draft
A32: 5 | B32: D5.09 | C32: Simulation — SW UA Task Error / Manual UA Exception | D32: 45 | E32: Simulation | F32: Facilitator Guide | G32: Job Aid | I32: ⚠️ DRAFT — I can resolve a Skywalker UA task and a manual UA exception in YODA. | J32: ⚠️ DRAFT — What does the exception say? What's the fix? | K32: Skywalker, YODA | M32: Draft
A33: 5 | B33: D5.10 | C33: Client Communication — Mock Emails, BOB Tenets | D33: 30 | E33: Activity | F33: Facilitator Guide | G33: Rubric | H33: Mock Email Set | I33: ⚠️ DRAFT — I can write a Day 5-level client email and self-grade against the rubric. | J33: ⚠️ DRAFT — Does this email pass the rubric? | K33: Email | M33: Draft
A34: 5 | B34: D5.11 | C34: EOD 5 Review | D34: 15 | E34: ILT | F34: Facilitator Guide | I34: ⚠️ DRAFT — I can summarize UA, MIMO/Stats, and documentation standards. | J34: ⚠️ DRAFT — What needs another pass tomorrow? | K34: Zoom | M34: Draft
A35: 6 | B35: D6.01 | C35: Day 6 Morning Review | D35: 15 | E35: ILT | F35: Facilitator Guide | I35: ⚠️ DRAFT — I can recall Day 5 concepts. | J35: ⚠️ DRAFT — Open questions? | K35: Zoom | L35: 1.5 practice / 1 hr admin time in afternoon | M35: Draft
A36: 6 | B36: D6.02 | C36: Meter Concepts: How Submetering Works & Why It Matters | D36: 30 | E36: ILT | F36: Facilitator Guide | G36: Slide Deck | I36: ⚠️ DRAFT — I understand what submetering is, how it differs from RUBS, and why properties choose it. | J36: ⚠️ DRAFT — Is this a submetered property? What does that mean for billing? | K36: Skywalker, YODA | M36: Draft
A37: 6 | B37: D6.03 | C37: Submetered Billing Methods & Math | D37: 60 | E37: ILT | F37: Facilitator Guide | G37: Job Aid | H37: Math Worksheet | I37: ⚠️ DRAFT — I can perform the math behind submetered billing — rates, usage, expense allocation. | J37: ⚠️ DRAFT — Did the math come out right? Does this rate match the contract? | K37: YODA, Skywalker, Calculator | M37: Draft
A38: 6 | B38: D6.04 | C38: Connecting Meters to the Workflow | D38: 30 | E38: ILT | F38: Facilitator Guide | G38: Job Aid | I38: ⚠️ DRAFT — I can place meter steps within the broader prep/calc workflow. | J38: ⚠️ DRAFT — Where do meters fit in this property's cycle? | K38: YODA, Skywalker | M38: Draft
A39: 6 | B39: D6.05 | C39: What Do You Need to Do — Step-by-Step Meter Review | D39: 45 | E39: Job Aid | F39: Facilitator Guide | G39: Step-by-Step Doc | I39: ⚠️ DRAFT — I can walk through a meter review checklist start to finish. | J39: ⚠️ DRAFT — Did I check every step? Anything missing? | K39: YODA, Skywalker, ABP | M39: Draft
A40: 6 | B40: D6.06 | C40: Verifying System Estimations & Initial Meter Reads | D40: 30 | E40: ILT | F40: Facilitator Guide | G40: Job Aid | I40: ⚠️ DRAFT — I can verify system-generated estimations and check initial meter reads before importing. | J40: ⚠️ DRAFT — Does the estimation make sense? Are the reads in range? | K40: YODA, ABP, Construct | M40: Draft
A41: 6 | B41: D6.07 | C41: Reading & Interpreting the Prop Cons / V3 Report | D41: 30 | E41: ILT | F41: Facilitator Guide | G41: Sample Report | I41: ⚠️ DRAFT — I can read the Property Consumption / V3 report and pull out what matters for troubleshooting. | J41: ⚠️ DRAFT — What anomalies do I see? What's normal here? | K41: Skywalker, YODA | M41: Draft
A42: 6 | B42: D6.08 | C42: Importing with ABP | D42: 30 | E42: Simulation | F42: Facilitator Guide | G42: Job Aid | I42: ⚠️ DRAFT — I can import initial reads and meter reads using ABP. | J42: ⚠️ DRAFT — Right import file? Right property? Right post month? | K42: ABP, YODA | M42: Draft
A43: 6 | B43: D6.09 | C43: Meter Estimation Practice: High-Repetition Scenarios | D43: 45 | E43: Activity | F43: Facilitator Guide | G43: Scenario Bank | I43: ⚠️ DRAFT — I can estimate meters across multiple scenarios with consistent accuracy. | J43: ⚠️ DRAFT — Which estimation method fits this scenario? | K43: YODA, Skywalker | L43: Repetition for fluency | M43: Draft
A44: 6 | B44: D6.10 | C44: Scenario — System / Mechanical Setup for Troubleshooting | D44: 30 | E44: Scenario | F44: Facilitator Guide | G44: Scenario Card | I44: ⚠️ DRAFT — I can diagnose meter issues stemming from system or mechanical setup. | J44: ⚠️ DRAFT — Setup issue or read issue? | K44: YODA, Skywalker | M44: Draft
A45: 6 | B45: D6.11 | C45: Simulation — SW Meter Task Error / Manual Meter Exception | D45: 45 | E45: Simulation | F45: Facilitator Guide | G45: Job Aid | I45: ⚠️ DRAFT — I can resolve a Skywalker meter task and a manual meter exception. | J45: ⚠️ DRAFT — What's the exception? What's the fix? | K45: Skywalker, YODA | M45: Draft
A46: 6 | B46: D6.12 | C46: Client Communication — Mock Emails, BOB Tenets | D46: 30 | E46: Activity | F46: Facilitator Guide | G46: Rubric | H46: Mock Email Set | I46: ⚠️ DRAFT — I can write a meter-related client email and self-grade. | J46: ⚠️ DRAFT — Does this explain the meter issue clearly? | K46: Email | M46: Draft
A47: 6 | B47: D6.13 | C47: EOD 6 Review | D47: 15 | E47: ILT | F47: Facilitator Guide | I47: ⚠️ DRAFT — I can summarize meters: concepts, math, workflow. | J47: ⚠️ DRAFT — What's still fuzzy? | K47: Zoom | M47: Draft
A48: 7 | B48: D7.01 | C48: Day 7 Morning Review | D48: 15 | E48: ILT | F48: Facilitator Guide | I48: ⚠️ DRAFT — I can recall meter concepts from Day 6. | J48: ⚠️ DRAFT — Open questions? | K48: Zoom | M48: Draft
A49: 7 | B49: D7.02 | C49: MIMO & Stats — Deeper Discussion | D49: 45 | E49: ILT | F49: Facilitator Guide | G49: Slide Deck | I49: ⚠️ DRAFT — I can interpret nuanced MIMO and stats situations beyond the basics. | J49: ⚠️ DRAFT — Edge case or standard? What's the right call? | K49: YODA, Skywalker | M49: Draft
A50: 7 | B50: D7.03 | C50: Depths of Billing Methods & Math | D50: 75 | E50: ILT | F50: Facilitator Guide | G50: Job Aid | H50: Math Worksheet | I50: ⚠️ DRAFT — I can apply billing methods at depth — RUBS variations, submetered nuances, factored occupancy, etc. | J50: ⚠️ DRAFT — Which method gives the right resident charge here? | K50: YODA, Skywalker | M50: Draft
A51: 7 | B51: D7.04 | C51: Rent-Only Bills | D51: 30 | E51: ILT | F51: Facilitator Guide | G51: Job Aid | I51: ⚠️ DRAFT — I can handle a rent-only billing scenario. | J51: ⚠️ DRAFT — Is rent the only charge here? Any utilities to add? | K51: YODA, Skywalker | M51: Draft
A52: 7 | B52: D7.05 | C52: Ramping | D52: 30 | E52: ILT | F52: Facilitator Guide | G52: Slide Deck | H52: Job Aid | I52: ⚠️ DRAFT — I understand what ramping is, when it applies, and how to set it up. | J52: ⚠️ DRAFT — Is this property ramping? At what rate? | K52: YODA, Skywalker | M52: Draft
A53: 7 | B53: D7.06 | C53: Billing Methods Application: Calculation Practice Activity | D53: 45 | E53: Activity | F53: Facilitator Guide | G53: Practice Set | I53: ⚠️ DRAFT — I can calculate resident charges across multiple billing methods accurately. | J53: ⚠️ DRAFT — Did my math match the expected output? | K53: Calculator, YODA | L53: Repetition for fluency | M53: Draft
A54: 7 | B54: D7.07 | C54: Scenario — Legal Dashboard Task | D54: 30 | E54: Scenario | F54: Facilitator Guide | G54: Scenario Card | I54: ⚠️ DRAFT — I can work through a legal dashboard task and identify what needs escalation. | J54: ⚠️ DRAFT — Legal flag — escalate or proceed? | K54: YODA, Legal Dashboard | M54: Draft
A55: 7 | B55: D7.08 | C55: Simulation — SW VA Meters with FCC / Manual TX Meters | D55: 60 | E55: Simulation | F55: Facilitator Guide | G55: Job Aid | I55: ⚠️ DRAFT — I can complete a Virginia meters task with FCC and a Texas manual meters task. | J55: ⚠️ DRAFT — State-specific regulation triggers — what changes? | K55: Skywalker, YODA, ABP | M55: Draft
A56: 7 | B56: D7.09 | C56: Client Communication — Meter Troubleshooting Mock Email | D56: 30 | E56: Activity | F56: Facilitator Guide | G56: Rubric | H56: Mock Email Set | I56: ⚠️ DRAFT — I can write a meter troubleshooting email to a client and self-grade. | J56: ⚠️ DRAFT — Did I explain the issue clearly without jargon? | K56: Email | M56: Draft
A57: 7 | B57: D7.10 | C57: EOD 7 Review | D57: 15 | E57: ILT | F57: Facilitator Guide | I57: ⚠️ DRAFT — I can summarize billing methods, ramping, and rent-only. | J57: ⚠️ DRAFT — Open questions before the harder Day 8 content? | K57: Zoom | M57: Draft
A58: 8 | B58: D8.01 | C58: Day 8 Morning Review | D58: 15 | E58: ILT | F58: Facilitator Guide | I58: ⚠️ DRAFT — I can recall Day 7 methods. | J58: ⚠️ DRAFT — Open questions? | K58: Zoom | M58: Draft
A59: 8 | B59: D8.02 | C59: Utility Messages | D59: 30 | E59: ILT | F59: Facilitator Guide | G59: Job Aid | I59: ⚠️ DRAFT — I can verify and update utility messages on resident bills. | J59: ⚠️ DRAFT — Is this message current? Correct for this property? | K59: YODA, Skywalker | M59: Draft
A60: 8 | B60: D8.03 | C60: Exceptions & Tasks | D60: 60 | E60: ILT | F60: Facilitator Guide | G60: Job Aid | H60: Reference List | I60: ⚠️ DRAFT — I can read, interpret, and resolve YODA exceptions and Skywalker tasks. | J60: ⚠️ DRAFT — What is this exception telling me? Resolve, escalate, or hand back? | K60: YODA, Skywalker | L60: FCC mechanics live here | M60: Draft
A61: 8 | B61: D8.04 | C61: Exception Note Standards: Good Note / Bad Note Deep Dive | D61: 30 | E61: ILT | F61: Facilitator Guide | G61: Example Notes | I61: ⚠️ DRAFT — I can write an exception note that meets standards and explain why bad notes cause downstream pain. | J61: ⚠️ DRAFT — Will this note hold up at QC? | K61: YODA, Skywalker | L61: Builds on Day 5 documentation | M61: Draft
A62: 8 | B62: D8.05 | C62: Reports | D62: 45 | E62: ILT | F62: Facilitator Guide | G62: Sample Reports | I62: ⚠️ DRAFT — I can pull and interpret the core reports I'll use daily (Property Consumption, Recovery QC, Vacant QC, Billing Summary). | J62: ⚠️ DRAFT — Which report answers this question? | K62: Skywalker, YODA | M62: Draft
A63: 8 | B63: D8.06 | C63: Critical Thinking | D63: 30 | E63: ILT | F63: Facilitator Guide | G63: Discussion Prompts | I63: ⚠️ DRAFT — I can apply critical thinking to ambiguous billing scenarios instead of pattern-matching. | J63: ⚠️ DRAFT — Am I assuming or verifying? | K63: Zoom | L63: Conceptual, soft skill | M63: Draft
A64: 8 | B64: D8.07 | C64: Prebill | D64: 45 | E64: ILT | F64: Facilitator Guide | G64: Job Aid | H64: Simulation | I64: ⚠️ DRAFT — I can generate a prebill, review it, and send it to the property for approval. | J64: ⚠️ DRAFT — Prebill required for this prop? Does it look right? | K64: Skywalker, YODA, Email | M64: Draft
A65: 8 | B65: D8.08 | C65: Formative Check: Pre-Skills Eval Self-Assessment | D65: 30 | E65: Assessment | F65: Self-Assessment Doc | G65: Facilitator Guide | I65: ⚠️ DRAFT — I know where I stand against the Day 9 Skills Eval criteria and what I need to study tonight. | J65: ⚠️ DRAFT — What are my weak areas? | K65: Self-assessment | L65: Pre-eval calibration | M65: Draft
A66: 8 | B66: D8.09 | C66: Scenario — Recovery Issue or U Exception | D66: 30 | E66: Scenario | F66: Facilitator Guide | G66: Scenario Card | I66: ⚠️ DRAFT — I can diagnose a recovery issue or U exception. | J66: ⚠️ DRAFT — What's the root cause? | K66: YODA, Skywalker | M66: Draft
A67: 8 | B67: D8.10 | C67: Simulation — SW Recovery Task / Manual U Exception | D67: 45 | E67: Simulation | F67: Facilitator Guide | G67: Job Aid | I67: ⚠️ DRAFT — I can resolve a Skywalker recovery task and a manual U exception. | J67: ⚠️ DRAFT — What's the exception saying? | K67: Skywalker, YODA | M67: Draft
A68: 8 | B68: D8.11 | C68: Client Communication — Prebill Client Response Mock Email | D68: 30 | E68: Activity | F68: Facilitator Guide | G68: Rubric | H68: Mock Email Set | I68: ⚠️ DRAFT — I can respond to a client's prebill questions in writing. | J68: ⚠️ DRAFT — Does my response answer the question and protect the relationship? | K68: Email | M68: Draft
A69: 8 | B69: D8.12 | C69: EOD 8 Review | D69: 15 | E69: ILT | F69: Facilitator Guide | I69: ⚠️ DRAFT — I can summarize exceptions, prebill, and reports. | J69: ⚠️ DRAFT — What do I need to drill tonight before the eval? | K69: Zoom | M69: Draft
A70: 9 | B70: D9.01 | C70: Day 9 Morning Review — Structured Eval Prep Review | D70: 30 | E70: ILT | F70: Facilitator Guide | G70: Review Doc | I70: ⚠️ DRAFT — I'm calibrated on the eval format, scope, and expectations. | J70: ⚠️ DRAFT — Where do I focus my last review minutes? | K70: Zoom | L70: Targeted pre-eval review | M70: Draft
A71: 9 | B71: D9.02 | C71: Billing Methodologies Math Practice | D71: 45 | E71: Activity | F71: Practice Set | G71: Facilitator Guide | I71: ⚠️ DRAFT — I can run billing math accurately under time pressure. | J71: ⚠️ DRAFT — Right method, right inputs, right output. | K71: Calculator, YODA | M71: Draft
A72: 9 | B72: D9.03 | C72: PMR Reads Activity | D72: 30 | E72: Activity | F72: Facilitator Guide | G72: Practice Set | I72: ⚠️ DRAFT — I can complete a Property Meter Read activity correctly. | J72: ⚠️ DRAFT — Reads in range? Estimations valid? | K72: Skywalker, YODA | M72: Draft
A73: 9 | B73: D9.04 | C73: Prebill Activity | D73: 30 | E73: Activity | F73: Facilitator Guide | G73: Practice Set | I73: ⚠️ DRAFT — I can generate and review a prebill in a practice scenario. | J73: ⚠️ DRAFT — Ready to send? | K73: Skywalker, YODA, Email | M73: Draft
A74: 9 | B74: D9.05 | C74: Bill Dates & FCC Activity | D74: 30 | E74: Activity | F74: Facilitator Guide | G74: Practice Set | I74: ⚠️ DRAFT — I can set bill dates including FCC scenarios. | J74: ⚠️ DRAFT — FCC needed here? | K74: YODA, Skywalker | M74: Draft
A75: 9 | B75: D9.06 | C75: Portfolio Prioritization Activity | D75: 30 | E75: Activity | F75: Facilitator Guide | G75: Scenario Set | I75: ⚠️ DRAFT — I can prioritize a sample portfolio by goal date, complexity, and risk. | J75: ⚠️ DRAFT — What do I touch first today? | K75: YODA, Skywalker, Calendar | M75: Draft
A76: 9 | B76: D9.07 | C76: Skills Evaluation | D76: 120 | E76: Assessment | F76: Eval Materials | G76: Facilitator Guide | H76: Rubric | I76: ⚠️ DRAFT — I demonstrate at or above 80% on the Skills Evaluation, confirming I'm ready to move into nesting. | J76: ⚠️ DRAFT — Demonstrate competence under eval conditions. | K76: YODA, Skywalker, Fusion 2.0 | L76: Pass threshold = 80% | M76: Draft
A77: 9 | B77: D9.08 | C77: Remediation Path for Learners Below 80% | D77: 30 | E77: ILT | F77: Remediation Plan | G77: Facilitator Guide | I77: ⚠️ DRAFT — If I scored below 80%, I know my remediation plan and timeline. If I scored at/above, I support peers. | J77: ⚠️ DRAFT — What's my next step? | K77: Eval rubric | L77: Branch-conditional | M77: Draft
A78: 9 | B78: D9.09 | C78: What Happens After I Submit a Property for QC? | D78: 30 | E78: ILT | F78: Facilitator Guide | G78: Flow Diagram | I78: ⚠️ DRAFT — I know the QC bin lifecycle, what handbacks look like, and how to respond when one comes back. | J78: ⚠️ DRAFT — Handback or pass-through? | K78: YODA, Skywalker | M78: Draft
A79: 9 | B79: D9.10 | C79: Client Communication — Mock Emails | D79: 30 | E79: Activity | F79: Facilitator Guide | G79: Rubric | H79: Mock Email Set | I79: ⚠️ DRAFT — I can handle eval-level client communication. | J79: ⚠️ DRAFT — Does this meet the rubric under eval conditions? | K79: Email | M79: Draft
A80: 9 | B80: D9.11 | C80: EOD 9 Review | D80: 15 | E80: ILT | F80: Facilitator Guide | I80: ⚠️ DRAFT — I know how I did on the eval and what comes next. | J80: ⚠️ DRAFT — Ready for Day 10? | K80: Zoom | M80: Draft
A81: 10 | B81: D10.01 | C81: Day 10 Morning Review | D81: 15 | E81: ILT | F81: Facilitator Guide | I81: ⚠️ DRAFT — I can recall the eval outcomes and any remediation steps. | J81: ⚠️ DRAFT — Open questions? | K81: Zoom | M81: Draft
A82: 10 | B82: D10.02 | C82: Customer Service Fundamentals | D82: 120 | E82: ILT | F82: Facilitator Guide | G82: Slide Deck | H82: Participant Workbook | I82: I understand the CSR department's role, how my billing work upstream affects CSR downstream, how to use CSR Alerts and Billing Reminders correctly, and the urgency standards for EWOK tickets. | J82: Does this need a CSR Alert? What's the right urgency threshold (24/48/5-day)? Reminder, Alert, or direct CSR contact? | K82: EWOK, YODA, Skywalker, Email, Knowledge Base | L82: Built, multiple review rounds complete | M82: Built
A83: 10 | B83: D10.03 | C83: Exporting | D83: 60 | E83: ILT | F83: Facilitator Guide | G83: Job Aid | H83: Simulation | I83: ⚠️ DRAFT — I can complete the export step that pushes charges to property systems via EDE. | J83: ⚠️ DRAFT — Right export settings? Right post month? | K83: YODA, Skywalker, Obiwan | L83: Step 06 of lifecycle | M83: Draft
A84: 10 | B84: D10.04 | C84: Portfolio Management | D84: 45 | E84: ILT | F84: Facilitator Guide | G84: Slide Deck | H84: Job Aid | I84: ⚠️ DRAFT — I can manage my portfolio: track goal dates, prioritize, communicate proactively with clients. | J84: ⚠️ DRAFT — What needs my attention first? | K84: YODA, Skywalker, Calendar, Email | M84: Draft
A85: 10 | B85: D10.05 | C85: A Day in the Life of a Billing Manager | D85: 45 | E85: ILT | F85: Facilitator Guide | G85: Slide Deck | I85: ⚠️ DRAFT — I have a realistic picture of a billing manager's day and the rhythm I'm stepping into. | J85: ⚠️ DRAFT — How will I structure my own day? | K85: Zoom | L85: Sets up nesting expectations | M85: Draft
A86: 10 | B86: D10.06 | C86: Stress Management & Daily Prioritization | D86: 30 | E86: ILT | F86: Facilitator Guide | G86: Discussion Prompts | I86: ⚠️ DRAFT — I have strategies for managing competing priorities and stress during high-volume periods. | J86: ⚠️ DRAFT — When I feel overwhelmed, what's my first move? | K86: N/A | L86: Soft skill, wellness | M86: Draft
A87: 10 | B87: D10.07 | C87: Program Wrap-Up & Nesting Preview | D87: 30 | E87: ILT | F87: Facilitator Guide | G87: Nesting Handout | I87: ⚠️ DRAFT — I know what nesting looks like, who my nesting support is, and what's expected of me in week 3+. | J87: ⚠️ DRAFT — What do I bring to my first nesting day? | K87: Zoom, Handout | L87: Transition to OTJ | M87: Draft
A88: 10 | B88: D10.08 | C88: Client Communication — Final Mock Emails | D88: 30 | E88: Activity | F88: Facilitator Guide | G88: Rubric | H88: Mock Email Set | I88: ⚠️ DRAFT — I can write Day-10-level client emails and self-assess against the rubric one final time. | J88: ⚠️ DRAFT — Does this clear the rubric bar consistently? | K88: Email | M88: Draft
A89: 10 | B89: D10.09 | C89: EOD 10 | D89: 15 | E89: ILT | F89: Facilitator Guide | I89: ⚠️ DRAFT — I can close out the program and move forward into nesting with clarity. | J89: ⚠️ DRAFT — What's my Day 11 plan? | K89: Zoom | L89: Program close | M89: Draft

Sheet Day Summary
A1: Billing EL Program — Day Summary
A2: Daily content budget: 540 min | Lunch + 2 breaks (90 min) auto-subtracted from the 10.5-hr day
A4: Day | B4: Scheduled Minutes | C4: Daily Budget | D4: Remaining | E4: Fill % | F4: Modules | G4: Draft Modules | H4: Status
A5: 3 | B5: =SUMIF('Content Inventory'!A:A,A5,'Content Inventory'!D:D) -> 400 | C5: 540 | D5: =C5-B5 -> 140 | E5: =IFERROR(B5/C5,0) -> 0.74074074 | F5: =COUNTIF('Content Inventory'!A:A,A5) -> 11 | G5: =COUNTIFS('Content Inventory'!A:A,A5,'Content Inventory'!M:M,"Draft") -> 8 | H5: =IF(B5>C5,"OVER",IF(B5=C5,"FULL",IF(B5>=C5*0.9,"NEAR FULL","UNDER"))) -> UNDER
A6: 4 | B6: =SUMIF('Content Inventory'!A:A,A6,'Content Inventory'!D:D) -> 365 | C6: 540 | D6: =C6-B6 -> 175 | E6: =IFERROR(B6/C6,0) -> 0.67592593 | F6: =COUNTIF('Content Inventory'!A:A,A6) -> 11 | G6: =COUNTIFS('Content Inventory'!A:A,A6,'Content Inventory'!M:M,"Draft") -> 10 | H6: =IF(B6>C6,"OVER",IF(B6=C6,"FULL",IF(B6>=C6*0.9,"NEAR FULL","UNDER"))) -> UNDER
A7: 5 | B7: =SUMIF('Content Inventory'!A:A,A7,'Content Inventory'!D:D) -> 380 | C7: 540 | D7: =C7-B7 -> 160 | E7: =IFERROR(B7/C7,0) -> 0.7037037 | F7: =COUNTIF('Content Inventory'!A:A,A7) -> 11 | G7: =COUNTIFS('Content Inventory'!A:A,A7,'Content Inventory'!M:M,"Draft") -> 11 | H7: =IF(B7>C7,"OVER",IF(B7=C7,"FULL",IF(B7>=C7*0.9,"NEAR FULL","UNDER"))) -> UNDER
A8: 6 | B8: =SUMIF('Content Inventory'!A:A,A8,'Content Inventory'!D:D) -> 435 | C8: 540 | D8: =C8-B8 -> 105 | E8: =IFERROR(B8/C8,0) -> 0.80555556 | F8: =COUNTIF('Content Inventory'!A:A,A8) -> 13 | G8: =COUNTIFS('Content Inventory'!A:A,A8,'Content Inventory'!M:M,"Draft") -> 13 | H8: =IF(B8>C8,"OVER",IF(B8=C8,"FULL",IF(B8>=C8*0.9,"NEAR FULL","UNDER"))) -> UNDER
A9: 7 | B9: =SUMIF('Content Inventory'!A:A,A9,'Content Inventory'!D:D) -> 375 | C9: 540 | D9: =C9-B9 -> 165 | E9: =IFERROR(B9/C9,0) -> 0.69444444 | F9: =COUNTIF('Content Inventory'!A:A,A9) -> 10 | G9: =COUNTIFS('Content Inventory'!A:A,A9,'Content Inventory'!M:M,"Draft") -> 10 | H9: =IF(B9>C9,"OVER",IF(B9=C9,"FULL",IF(B9>=C9*0.9,"NEAR FULL","UNDER"))) -> UNDER
A10: 8 | B10: =SUMIF('Content Inventory'!A:A,A10,'Content Inventory'!D:D) -> 405 | C10: 540 | D10: =C10-B10 -> 135 | E10: =IFERROR(B10/C10,0) -> 0.75 | F10: =COUNTIF('Content Inventory'!A:A,A10) -> 12 | G10: =COUNTIFS('Content Inventory'!A:A,A10,'Content Inventory'!M:M,"Draft") -> 12 | H10: =IF(B10>C10,"OVER",IF(B10=C10,"FULL",IF(B10>=C10*0.9,"NEAR FULL","UNDER"))) -> UNDER
A11: 9 | B11: =SUMIF('Content Inventory'!A:A,A11,'Content Inventory'!D:D) -> 420 | C11: 540 | D11: =C11-B11 -> 120 | E11: =IFERROR(B11/C11,0) -> 0.77777778 | F11: =COUNTIF('Content Inventory'!A:A,A11) -> 11 | G11: =COUNTIFS('Content Inventory'!A:A,A11,'Content Inventory'!M:M,"Draft") -> 11 | H11: =IF(B11>C11,"OVER",IF(B11=C11,"FULL",IF(B11>=C11*0.9,"NEAR FULL","UNDER"))) -> UNDER
A12: 10 | B12: =SUMIF('Content Inventory'!A:A,A12,'Content Inventory'!D:D) -> 390 | C12: 540 | D12: =C12-B12 -> 150 | E12: =IFERROR(B12/C12,0) -> 0.72222222 | F12: =COUNTIF('Content Inventory'!A:A,A12) -> 9 | G12: =COUNTIFS('Content Inventory'!A:A,A12,'Content Inventory'!M:M,"Draft") -> 8 | H12: =IF(B12>C12,"OVER",IF(B12=C12,"FULL",IF(B12>=C12*0.9,"NEAR FULL","UNDER"))) -> UNDER
A13: TOTAL | B13: =SUM(B5:B12) -> 3170 | C13: =SUM(C5:C12) -> 4320 | D13: =C13-B13 -> 1150 | E13: =IFERROR(B13/C13,0) -> 0.7337963 | F13: =SUM(F5:F12) -> 88 | G13: =SUM(G5:G12) -> 83

Sheet Week View
A1: Week View
A3: Week | B3: Days | C3: Total Scheduled Min | D3: Total Budget | E3: Fill % | F3: Total Modules
A4: Week 1 (Days 3-5) | B4: 3, 4, 5 | C4: ='Day Summary'!B5+'Day Summary'!B6+'Day Summary'!B7 -> 1145 | D4: ='Day Summary'!C5+'Day Summary'!C6+'Day Summary'!C7 -> 1620 | E4: =IFERROR(C4/D4,0) -> 0.70679012 | F4: ='Day Summary'!F5+'Day Summary'!F6+'Day Summary'!F7 -> 33
A5: Week 2 (Days 6-10) | B5: 6, 7, 8, 9, 10 | C5: ='Day Summary'!B8+'Day Summary'!B9+'Day Summary'!B10+'Day Summary'!B11+'Day Summary'!B12 -> 2025 | D5: ='Day Summary'!C8+'Day Summary'!C9+'Day Summary'!C10+'Day Summary'!C11+'Day Summary'!C12 -> 2700 | E5: =IFERROR(C5/D5,0) -> 0.75 | F5: ='Day Summary'!F8+'Day Summary'!F9+'Day Summary'!F10+'Day Summary'!F11+'Day Summary'!F12 -> 55

Sheet Legend
A1: Dashboard Legend & Settings
A3: Status Codes
A4: Built | B4: Content is finalized or in active stakeholder review.
A5: Draft | B5: ⚠️ Auto-filled best-guess. Needs SME review before finalization.
A8: Content Type Colors
A9: ILT
A10: eLearning
A11: Blended
A12: Simulation
A13: Scenario
A14: Activity
A15: Assessment
A16: Job Aid
A17: OTJ
A20: Time Math
A21: Daily content budget | B21: 540 min (9 hours)
A22: Lunch (auto-subtracted from total day) | B22: 60 min
A23: Breaks (2 × 15 min, auto-subtracted) | B23: 30 min
A24: Total non-content time per day | B24: 90 min
A25: Implied total class day | B25: 630 min (10.5 hrs) — adjust to your schedule
A27: OTJ Handling
A28: Tag OTJ rows with Content Type = 'OTJ' in Content Inventory.
A29: OTJ counts toward the day's total minutes AND appears as its own block in day views.
